gcsfs/__init__.py
gcsfs/_version.py
gcsfs/checkers.py
gcsfs/core.py
gcsfs/credentials.py
gcsfs/dask_link.py
gcsfs/inventory_report.py
gcsfs/mapping.py
gcsfs/retry.py
gcsfs/cli/__init__.py
gcsfs/cli/gcsfuse.py
gcsfs-2025.3.1.dist-info/licenses/LICENSE.txt
gcsfs-2025.3.1.dist-info/METADATA
gcsfs-2025.3.1.dist-info/WHEEL
gcsfs-2025.3.1.dist-info/top_level.txt
gcsfs-2025.3.1.dist-info/RECORD
